cnspy_rosbag2image/ImageFormatTypes.py
cnspy_rosbag2image/ROSMessageTypes.py
cnspy_rosbag2image/ROSbag2Image.py
cnspy_rosbag2image/__init__.py
test/__init__.py
test/test_ROSbag2Image.py
cnspy_rosbag2image-0.1.2.dist-info/LICENCE
cnspy_rosbag2image-0.1.2.dist-info/METADATA
cnspy_rosbag2image-0.1.2.dist-info/WHEEL
cnspy_rosbag2image-0.1.2.dist-info/entry_points.txt
cnspy_rosbag2image-0.1.2.dist-info/top_level.txt
cnspy_rosbag2image-0.1.2.dist-info/RECORD
