Metadata-Version: 2.1
Name: cnspy_rosbag2image
Version: 0.1.2
Summary: ROS1 rosbag to image file converter.
Home-page: https://github.com/aau-cns/cnspy_rosbag2image/
Author: Roland Jung
Author-email: roland.jung@aau.at
Project-URL: Bug Tracker, https://github.com/aau-cns/cnspy_rosbag2image/issues
Classifier: Development Status :: 4 - Beta
Classifier: Intended Audience :: Developers
Classifier: Programming Language :: Python :: 3
Classifier: License :: OSI Approved :: GNU General Public License v3 (GPLv3)
Classifier: Operating System :: OS Independent
Requires-Python: >=3.6
License-File: LICENCE
Requires-Dist: numpy
Requires-Dist: tqdm
Requires-Dist: pandas
Requires-Dist: argparse
Requires-Dist: PyYAML
Requires-Dist: rospkg
Requires-Dist: opencv-python
Requires-Dist: pycryptodomex
Requires-Dist: pycryptodome
Requires-Dist: gnupg
Requires-Dist: lz4
